README.md
setup.cfg
setup.py
brkt_cli/__init__.py
brkt_cli/argutil.py
brkt_cli/auth.py
brkt_cli/encryptor_service.py
brkt_cli/instance_config.py
brkt_cli/instance_config_args.py
brkt_cli/make_token.py
brkt_cli/mv_version.py
brkt_cli/proxy.py
brkt_cli/subcommand.py
brkt_cli/test_encryptor_service.py
brkt_cli/test_instance_config.py
brkt_cli/test_mv_version.py
brkt_cli/test_user_data.py
brkt_cli/test_util.py
brkt_cli/test_validation.py
brkt_cli/test_version.py
brkt_cli/user_data.py
brkt_cli/util.py
brkt_cli/validation.py
brkt_cli/version.py
brkt_cli/yeti.py
brkt_cli.egg-info/PKG-INFO
brkt_cli.egg-info/SOURCES.txt
brkt_cli.egg-info/dependency_links.txt
brkt_cli.egg-info/entry_points.txt
brkt_cli.egg-info/not-zip-safe
brkt_cli.egg-info/requires.txt
brkt_cli.egg-info/top_level.txt
brkt_cli/aws/__init__.py
brkt_cli/aws/aws_args.py
brkt_cli/aws/aws_constants.py
brkt_cli/aws/aws_service.py
brkt_cli/aws/boto3_device.py
brkt_cli/aws/boto3_tag.py
brkt_cli/aws/encrypt_ami.py
brkt_cli/aws/encrypt_ami_args.py
brkt_cli/aws/model.py
brkt_cli/aws/share_logs.py
brkt_cli/aws/share_logs_args.py
brkt_cli/aws/test_aws.py
brkt_cli/aws/test_aws_service.py
brkt_cli/aws/test_encrypt_ami.py
brkt_cli/aws/test_share_logs.py
brkt_cli/aws/test_update_ami.py
brkt_cli/aws/test_wrap_guest_image.py
brkt_cli/aws/update_ami.py
brkt_cli/aws/update_encrypted_ami_args.py
brkt_cli/aws/wrap_image.py
brkt_cli/aws/wrap_image_args.py
brkt_cli/aws/wrap_instance_args.py
brkt_cli/brkt_jwt/__init__.py
brkt_cli/brkt_jwt/jwk.py
brkt_cli/brkt_jwt/test_jwt.py
brkt_cli/config/__init__.py
brkt_cli/config/test_config.py
brkt_cli/crypto/__init__.py
brkt_cli/crypto/test_crypto.py
brkt_cli/esx/__init__.py
brkt_cli/esx/assign_static_ip_args.py
brkt_cli/esx/encrypt_vmdk.py
brkt_cli/esx/encrypt_vmdk_args.py
brkt_cli/esx/encrypt_with_esx_host_args.py
brkt_cli/esx/esx_args.py
brkt_cli/esx/esx_service.py
brkt_cli/esx/rescue_metavisor.py
brkt_cli/esx/rescue_metavisor_args.py
brkt_cli/esx/update_encrypted_vmdk_args.py
brkt_cli/esx/update_vmdk.py
brkt_cli/esx/update_with_esx_host_args.py
brkt_cli/esx/wrap_image.py
brkt_cli/esx/wrap_with_esx_host_args.py
brkt_cli/esx/wrap_with_vcenter_args.py
brkt_cli/gcp/__init__.py
brkt_cli/gcp/encrypt_gcp_image.py
