Metadata-Version: 1.0
Name: brkt-cli
Version: 1.0.15
Summary: Bracket Computing command line interface
Home-page: http://brkt.com
Author: UNKNOWN
Author-email: UNKNOWN
License: Apache 2.0
Platform: UNKNOWN
